bfiocpp/libbfiocpp.cp310-win_amd64.pyd
bfiocpp/tsreader.py
bfiocpp/tswriter.py
bfiocpp/_version.py
bfiocpp/__init__.py
bfiocpp-0.3.2.dist-info/DELVEWHEEL
bfiocpp-0.3.2.dist-info/LICENSE
bfiocpp-0.3.2.dist-info/METADATA
bfiocpp-0.3.2.dist-info/RECORD
bfiocpp-0.3.2.dist-info/top_level.txt
bfiocpp-0.3.2.dist-info/WHEEL
bfiocpp.libs/msvcp140-3d1ddc0560f37b11c02c0bcd16995d01.dll
