Metadata-Version: 2.2
Name: bfiocpp
Version: 0.3.2
Summary: Tensorstore Based Backend for BFIO
Home-page: https://github.com/PolusAI/bfiocpp
Author: Sameeul Bashir Samee
Author-email: sameeul.samee@axleinfo.com
Requires-Python: >=3.8
License-File: LICENSE
Requires-Dist: numpy
Dynamic: author
Dynamic: author-email
Dynamic: description
Dynamic: description-content-type
Dynamic: home-page
Dynamic: requires-dist
Dynamic: requires-python
Dynamic: summary
